BruteSleuth-1.4.3.data/scripts/brutesleuth
brutesleuth/__init__.py
BruteSleuth-1.4.3.dist-info/LICENSE
BruteSleuth-1.4.3.dist-info/METADATA
BruteSleuth-1.4.3.dist-info/WHEEL
BruteSleuth-1.4.3.dist-info/top_level.txt
BruteSleuth-1.4.3.dist-info/RECORD
