Metadata-Version: 2.1
Name: BruteSleuth
Version: 1.4.3
Summary: Making bruteforce wordlists smarter, not harder
Home-page: https://github.com/rad10/BruteSleuth
Download-URL: https://github.com/rad10/BruteSleuth/releases
Author: Nicholas Cottrell
Author-email: ncottrellweb@gmail.com
License: GPL-3.0 License
Project-URL: Bug Tracker, https://github.com/rad10/BruteSleuth/issues
Keywords: bruteforce,wordlist,permutation,wordlist-generator,wordlists,bruteforce-wordlist,bruteforce-tools
Platform: any
Classifier: Programming Language :: Python :: 3
Classifier: License :: OSI Approved :: MIT License
Classifier: Operating System :: OS Independent
Provides: brutesleuth
Requires-Python: >=3.6
License-File: LICENSE
